README.md
setup.py
Pyvirertory/Everykey.py
Pyvirertory/__init__.py
Pyvirertory.egg-info/PKG-INFO
Pyvirertory.egg-info/SOURCES.txt
Pyvirertory.egg-info/dependency_links.txt
Pyvirertory.egg-info/top_level.txt