Metadata-Version: 2.1
Name: Pyvirertory
Version: 1.0.0
Summary: This third-party library makes it possible to quickly build simple virtual characters, have simple conversations with AI, and conduct personalized training. It's not particularly smart, but it's great for Python beginners.
Home-page: UNKNOWN
License: UNKNOWN
Platform: UNKNOWN
